FiniteConsole/FiniteConsole.py
FiniteConsole/__init__.py
FiniteConsole/exceptions.py
FiniteConsole-1.0.2.dist-info/LICENSE
FiniteConsole-1.0.2.dist-info/METADATA
FiniteConsole-1.0.2.dist-info/WHEEL
FiniteConsole-1.0.2.dist-info/top_level.txt
FiniteConsole-1.0.2.dist-info/RECORD
