Metadata-Version: 2.1
Name: FiniteConsole
Version: 1.0.2
Summary: A way to simplify development of CLI applications
Home-page: https://github.com/cyrillelamal/FiniteConsole
Author: Cyrille Kossyguine
Author-email: lambda_man@outlook.fr
License: MIT
Platform: UNKNOWN
Classifier: Programming Language :: Python :: 3
Classifier: License :: OSI Approved :: MIT License
Classifier: Operating System :: OS Independent
Requires-Python: >=3.6
